README.rst
setup.cfg
setup.py
pingscan/__init__.py
pingscan/c_icmp.c
pingscan/compat.py
pingscan/icmp.py
pingscan/pingscan.py
pingscan/resources.py
pingscan/utils.py
pingscan.egg-info/PKG-INFO
pingscan.egg-info/SOURCES.txt
pingscan.egg-info/dependency_links.txt
pingscan.egg-info/top_level.txt