Metadata-Version: 1.1
Name: pingscan
Version: 1.0.2
Summary: A multiprocessing async ping scanner
Home-page: https://github.com/Cashmaney/pingscan
Author: Itzik Grossman
Author-email: itzygro@gmail.com
License: MIT License
Platform: UNKNOWN
Classifier: Programming Language :: Python
Classifier: Programming Language :: Cython
Classifier: Natural Language :: English
Classifier: Environment :: Plugins
Classifier: Intended Audience :: Developers
Classifier: License :: OSI Approved :: MIT License
Classifier: Operating System :: POSIX :: Linux
Classifier: Topic :: System :: Monitoring
Classifier: Topic :: Software Development :: Libraries :: Python Modules
